git_substitute/__init__.py
git_substitute/__main__.py
git_substitute/tool.py
git_substitute-0.1.2.dist-info/entry_points.txt
git_substitute-0.1.2.dist-info/METADATA
git_substitute-0.1.2.dist-info/WHEEL
git_substitute-0.1.2.dist-info/RECORD
