Metadata-Version: 2.1
Name: git-substitute
Version: 0.1.2
Summary: 
Author: Robert Roos
Author-email: robert.soor@gmail.com
Requires-Python: >=3.10,<4.0
Classifier: Programming Language :: Python :: 3
Classifier: Programming Language :: Python :: 3.10
Classifier: Programming Language :: Python :: 3.11
Classifier: Programming Language :: Python :: 3.12
Classifier: Programming Language :: Python :: 3.13
Requires-Dist: gitpython (>=3.1.43,<4.0.0)
